multi_time_series_connectedness/__init__.py
multi_time_series_connectedness/coef.py
multi_time_series_connectedness/connectedness.py
multi_time_series_connectedness/rolling_connectedness.py
multi_time_series_connectedness/volatility.py
multi_time_series_connectedness-0.2.2.dist-info/LICENSE
multi_time_series_connectedness-0.2.2.dist-info/METADATA
multi_time_series_connectedness-0.2.2.dist-info/WHEEL
multi_time_series_connectedness-0.2.2.dist-info/RECORD
