Metadata-Version: 2.1
Name: multi-time-series-connectedness
Version: 0.2.2
Summary: 
License: MIT
Author: Victor Chen
Author-email: victor.yccchen1@gmail.com
Requires-Python: >=3.10
Classifier: License :: OSI Approved :: MIT License
Classifier: Programming Language :: Python :: 3
Classifier: Programming Language :: Python :: 3.10
Classifier: Programming Language :: Python :: 3.11
Classifier: Programming Language :: Python :: 3.12
Requires-Dist: coverage (==7.6.1)
Requires-Dist: pandas (==2.2.3)
Requires-Dist: scikit-learn (==1.5.2)
Project-URL: repository, https://github.com/YCChenVictor/multi_time_series_connectedness
